simpleros/__init__.py
simpleros/core.py
simpleros/msg/__init__.py
simpleros/msg/std_msg.capnp
simpleros/msg/std_msg.py
simpleros-0.0.1.dist-info/licenses/LICENSE
simpleros-0.0.1.dist-info/METADATA
simpleros-0.0.1.dist-info/WHEEL
simpleros-0.0.1.dist-info/top_level.txt
simpleros-0.0.1.dist-info/RECORD
